sinapsis_elevenlabs/__init__.py
sinapsis_elevenlabs/helpers/__init__.py
sinapsis_elevenlabs/helpers/env_var_keys.py
sinapsis_elevenlabs/helpers/tags.py
sinapsis_elevenlabs/helpers/voice_utils.py
sinapsis_elevenlabs/templates/__init__.py
sinapsis_elevenlabs/templates/elevenlabs_base.py
sinapsis_elevenlabs/templates/elevenlabs_sts.py
sinapsis_elevenlabs/templates/elevenlabs_tts.py
sinapsis_elevenlabs/templates/elevenlabs_voice_clone.py
sinapsis_elevenlabs/templates/elevenlabs_voice_generation.py
sinapsis_elevenlabs-0.2.4.dist-info/licenses/LICENSE
sinapsis_elevenlabs-0.2.4.dist-info/METADATA
sinapsis_elevenlabs-0.2.4.dist-info/WHEEL
sinapsis_elevenlabs-0.2.4.dist-info/top_level.txt
sinapsis_elevenlabs-0.2.4.dist-info/RECORD
