Metadata-Version: 2.4
Name: sinapsis-elevenlabs
Version: 0.2.4
Summary: Generate realistic voices from text, other speeches, and more using the Elevenlabs library.
Author-email: SinapsisAI <dev@sinapsis.tech>
Project-URL: Homepage, https://sinapsis.tech
Project-URL: Documentation, https://docs.sinapsis.tech/docs
Project-URL: Tutorials, https://docs.sinapsis.tech/tutorials
Project-URL: Repository, https://github.com/Sinapsis-AI/sinapsis-speech.git
Requires-Python: >=3.10
License-File: LICENSE
Requires-Dist: elevenlabs>=1.50.3
Requires-Dist: sinapsis>=0.2.2
Provides-Extra: data-tools
Requires-Dist: sinapsis-data-readers>=0.1.2; extra == "data-tools"
Provides-Extra: all
Requires-Dist: sinapsis-elevenlabs[data-tools]; extra == "all"
Dynamic: license-file
